odoo/addons/account_followup_due_filter/LICENSE
odoo/addons/account_followup_due_filter/README.rst
odoo/addons/account_followup_due_filter/__init__.py
odoo/addons/account_followup_due_filter/__manifest__.py
odoo/addons/account_followup_due_filter/images/screen.png
odoo/addons/account_followup_due_filter/models/__init__.py
odoo/addons/account_followup_due_filter/models/res_partner.py
odoo/addons/account_followup_due_filter/static/description/icon.png
odoo/addons/account_followup_due_filter/static/description/index.html
odoo_addon_account_followup_due_filter-18.0.1.0.0.dist-info/METADATA
odoo_addon_account_followup_due_filter-18.0.1.0.0.dist-info/WHEEL
odoo_addon_account_followup_due_filter-18.0.1.0.0.dist-info/top_level.txt
odoo_addon_account_followup_due_filter-18.0.1.0.0.dist-info/RECORD
